{"ntwbt7zEc5KY72CaAlSRgQ==":"mbr-2000x1335.jpg","SXq9hxw7qIFFb7AErrtGWA==":"7-600x600-600x600.jpg","S+hbbTe63NgZPLXYq+Dj4Q==":"bigstock-katy-perry-at-the-the-smurfs--600x900.jpg","3op+rCY4htFmjG/PUuFfIw==":"bigstock-katy-perry-at-the-the-smurfs--600x781.jpg","wBR6jvEaTLJwXGSdyKRc1A==":"gyan%20photo1%20(1)-600x600.jpg","oHnUINh+plmV3Qd1EE7a9A==":"bigstock-katy-perry-at-the-the-smurfs--600x557.jpg","3KuzOudxB17FLgNZdJBM1g==":"gyan%20photo1%20(1)%20(1)-600x557.jpg","67eY2gGnqKxclvu/iaM8pw==":"personal-branding-guy_dpc-2000x1500.jpg","vMUZBQycvpdU5sY1OKWn4A==":"gyan%20photo1%20(1)%20(1)%20-%20copy-600x559.jpg","LqSpmgkrpEotg2jAClSxpw==":"gyan%20photo1%20(1)%20(1)-600x557.jpg","xdIcWaDM5yFIocqUuOqUOQ==":"p_20150508-600x765.jpg","UpuLJWy+GBFF7HdDFbeBRA==":"p_20150508-600x627.jpg","jnkpROsUQaCJgikUsfiUCw==":"p_20150508-600x630.jpg","husf3uzg6HtoZ6bRWezU9w==":"p_20150508-600x678.jpg","bqvF+Vjhl1sbBEMAxktrMw==":"p_20150508-600x557.jpg"}